hypernetx/__init__.py
hypernetx/algorithms/__init__.py
hypernetx/algorithms/contagion.py
hypernetx/algorithms/generative_models.py
hypernetx/algorithms/homology_mod2.py
hypernetx/algorithms/hypergraph_modularity.py
hypernetx/algorithms/laplacians_clustering.py
hypernetx/algorithms/matching_algorithms.py
hypernetx/algorithms/s_centrality_measures.py
hypernetx/classes/__init__.py
hypernetx/classes/factory.py
hypernetx/classes/hyp_view.py
hypernetx/classes/hypergraph.py
hypernetx/classes/incidence_store.py
hypernetx/classes/property_store.py
hypernetx/drawing/__init__.py
hypernetx/drawing/rubber_band.py
hypernetx/drawing/two_column.py
hypernetx/drawing/util.py
hypernetx/exception.py
hypernetx/hif.py
hypernetx/reports/__init__.py
hypernetx/reports/descriptive_stats.py
hypernetx/utils/__init__.py
hypernetx/utils/decorators.py
hypernetx/utils/extras.py
hypernetx/utils/log.py
hypernetx/utils/toys/ChungLuTransmissionData.csv
hypernetx/utils/toys/GoT.pkl
hypernetx/utils/toys/HarryPotterHypergraph.p
hypernetx/utils/toys/HarryPotter_Characters.csv
hypernetx/utils/toys/__init__.py
hypernetx/utils/toys/disGene.txt
hypernetx/utils/toys/gene_data.py
hypernetx/utils/toys/harrypotter.py
hypernetx/utils/toys/lesmis.py
hypernetx/utils/toys/transmission_problem.py
hypernetx-2.3.10.dist-info/LICENSE.rst
hypernetx-2.3.10.dist-info/METADATA
hypernetx-2.3.10.dist-info/WHEEL
hypernetx-2.3.10.dist-info/RECORD
