Metadata-Version: 2.1
Name: hypernetx
Version: 2.3.10
Summary: HyperNetX is a Python library for the creation and study of hypergraphs.
Home-page: https://pypi.org/project/hypernetx/
License: 3-Clause BSD license
Keywords: hypergraphs
Author: Brenda Praggastis
Author-email: Brenda.Praggastis@pnnl.gov
Requires-Python: >=3.10,<4.0.0
Classifier: License :: Other/Proprietary License
Classifier: Programming Language :: Python :: 3
Classifier: Programming Language :: Python :: 3.10
Classifier: Programming Language :: Python :: 3.11
Classifier: Programming Language :: Python :: 3.12
Classifier: Programming Language :: Python :: 3.13
Requires-Dist: celluloid (>=0.2.0)
Requires-Dist: decorator (>=5.1.1)
Requires-Dist: igraph (>=0.11.4)
Requires-Dist: networkx (>=3.3)
Requires-Dist: pandas (>=2.2.2)
Requires-Dist: requests (>=2.32.3,<3.0.0)
Requires-Dist: scikit-learn (>=1.4.2)
Requires-Dist: scipy (>=1.13)
Project-URL: Documentation, https://hypernetx.readthedocs.io/en/latest/
Project-URL: Repository, https://github.com/pnnl/HyperNetX
